odoo/addons/account_invoice_date_due/README.rst
odoo/addons/account_invoice_date_due/__init__.py
odoo/addons/account_invoice_date_due/__manifest__.py
odoo/addons/account_invoice_date_due/i18n/account_invoice_date_due.pot
odoo/addons/account_invoice_date_due/i18n/es.po
odoo/addons/account_invoice_date_due/security/security.xml
odoo/addons/account_invoice_date_due/static/description/icon.png
odoo/addons/account_invoice_date_due/wizards/__init__.py
odoo/addons/account_invoice_date_due/wizards/update_due_date.py
odoo/addons/account_invoice_date_due/wizards/update_due_date_views.xml
odoo12_addon_account_invoice_date_due-12.0.1.1.0.dist-info/METADATA
odoo12_addon_account_invoice_date_due-12.0.1.1.0.dist-info/WHEEL
odoo12_addon_account_invoice_date_due-12.0.1.1.0.dist-info/top_level.txt
odoo12_addon_account_invoice_date_due-12.0.1.1.0.dist-info/RECORD
